v2ray_util/__init__.py
v2ray_util/main.py
v2ray_util/config_modify/__init__.py
v2ray_util/config_modify/base.py
v2ray_util/config_modify/cdn.py
v2ray_util/config_modify/multiple.py
v2ray_util/config_modify/ss.py
v2ray_util/config_modify/stream.py
v2ray_util/config_modify/tls.py
v2ray_util/global_setting/__init__.py
v2ray_util/global_setting/ban_bt.py
v2ray_util/global_setting/calcul_traffic.sh
v2ray_util/global_setting/clean_iptables.sh
v2ray_util/global_setting/clean_traffic.sh
v2ray_util/global_setting/iptables_ctr.py
v2ray_util/global_setting/stats_ctr.py
v2ray_util/global_setting/update_timer.py
v2ray_util/json_template/dyn_port.json
v2ray_util/json_template/http.json
v2ray_util/json_template/http2.json
v2ray_util/json_template/kcp.json
v2ray_util/json_template/mtproto.json
v2ray_util/json_template/quic.json
v2ray_util/json_template/reality.json
v2ray_util/json_template/server.json
v2ray_util/json_template/socks.json
v2ray_util/json_template/ss.json
v2ray_util/json_template/stats_settings.json
v2ray_util/json_template/tcp.json
v2ray_util/json_template/vless.json
v2ray_util/json_template/ws.json
v2ray_util/locale_i18n/en_US/LC_MESSAGES/lang.mo
v2ray_util/locale_i18n/zh_CH/LC_MESSAGES/lang.mo
v2ray_util/util_core/__init__.py
v2ray_util/util_core/config.py
v2ray_util/util_core/group.py
v2ray_util/util_core/loader.py
v2ray_util/util_core/profile.py
v2ray_util/util_core/selector.py
v2ray_util/util_core/trans.py
v2ray_util/util_core/util.cfg
v2ray_util/util_core/utils.py
v2ray_util/util_core/v2ray.py
v2ray_util/util_core/writer.py
v2ray_util-3.11.4.dist-info/LICENSE
v2ray_util-3.11.4.dist-info/METADATA
v2ray_util-3.11.4.dist-info/WHEEL
v2ray_util-3.11.4.dist-info/entry_points.txt
v2ray_util-3.11.4.dist-info/top_level.txt
v2ray_util-3.11.4.dist-info/RECORD
