Metadata-Version: 2.1
Name: v2ray-util
Version: 3.11.4
Summary: a tool to manage v2ray config json
Home-page: https://github.com/Jrohy/multi-v2ray
Author: Jrohy
Author-email: euvkzx@gmail.com
License: GPL
Keywords: python v2ray multi-v2ray vmess socks5 vless trojan xray xtls reality
Classifier: Topic :: Utilities
Classifier: Development Status :: 5 - Production/Stable
Classifier: License :: OSI Approved :: GNU General Public License v3 (GPLv3)
Classifier: Natural Language :: English
Classifier: Natural Language :: Chinese (Simplified)
Classifier: Programming Language :: Python :: 3
Classifier: Programming Language :: Python :: 3.4
Classifier: Programming Language :: Python :: 3.5
Classifier: Programming Language :: Python :: 3.6
Classifier: Programming Language :: Python :: 3.7
Classifier: Programming Language :: Python :: 3.8
Classifier: Programming Language :: Python :: 3.9
Classifier: Programming Language :: Python :: 3.10
Classifier: Programming Language :: Python :: 3.11
Requires-Python: >=3
License-File: LICENSE
